{"post_stream":{"posts":[{"id":3657,"name":"","username":"practicing01","avatar_template":"https://avatars.discourse-cdn.com/v4/letter/p/b5e925/{size}.png","created_at":"2014-12-17T11:32:30.000Z","cooked":"\u003cp\u003e[video]\u003ca href=\"https://www.youtube.com/watch?v=N9Me64RjV-8%5B/video%5D\" rel=\"nofollow noopener\"\u003ehttps://www.youtube.com/watch?v=N9Me64RjV-8[/video]\u003c/a\u003e\u003cbr\u003e\n\u003ca href=\"https://play.google.com/store/apps/details?id=com.mds.cof\" data-bbcode=\"true\" rel=\"nofollow noopener\"\u003ehttps://play.google.com/store/apps/details?id=com.mds.cof\u003c/a\u003e\u003cbr\u003e\nMy first c++/Urho3D game release.  It’s not great but it does have fun factor!\u003c/p\u003e","post_number":1,"post_type":1,"updated_at":"2017-01-02T01:02:03.026Z","reply_count":0,"reply_to_post_number":null,"quote_count":0,"incoming_link_count":2,"reads":2,"readers_count":1,"score":10.4,"yours":false,"topic_id":675,"topic_slug":"claus-of-fury","display_username":"","primary_group_name":null,"flair_name":null,"flair_url":null,"flair_bg_color":null,"flair_color":null,"version":1,"can_edit":false,"can_delete":false,"can_recover":false,"can_wiki":false,"link_counts":[{"url":"https://www.youtube.com/watch?v=N9Me64RjV-8%5B/video%5D","internal":false,"reflection":false,"title":"Claus of Fury","clicks":4},{"url":"https://play.google.com/store/apps/details?id=com.mds.cof","internal":false,"reflection":false,"clicks":2}],"read":true,"user_title":null,"bookmarked":false,"actions_summary":[],"moderator":false,"admin":false,"staff":false,"user_id":140,"hidden":false,"trust_level":1,"deleted_at":null,"user_deleted":false,"edit_reason":null,"can_view_edit_history":true,"wiki":false,"can_accept_answer":false,"can_unaccept_answer":false,"accepted_answer":false},{"id":3677,"name":"","username":"att","avatar_template":"https://avatars.discourse-cdn.com/v4/letter/a/bcef8e/{size}.png","created_at":"2014-12-18T02:54:14.000Z","cooked":"\u003cp\u003eGood, but on my nexus 4 device, the building always blink.\u003c/p\u003e","post_number":2,"post_type":1,"updated_at":"2017-01-02T01:02:04.591Z","reply_count":0,"reply_to_post_number":null,"quote_count":0,"incoming_link_count":1,"reads":2,"readers_count":1,"score":5.4,"yours":false,"topic_id":675,"topic_slug":"claus-of-fury","display_username":"","primary_group_name":null,"flair_name":null,"flair_url":null,"flair_bg_color":null,"flair_color":null,"version":1,"can_edit":false,"can_delete":false,"can_recover":false,"can_wiki":false,"read":true,"user_title":null,"bookmarked":false,"actions_summary":[],"moderator":false,"admin":false,"staff":false,"user_id":48,"hidden":false,"trust_level":2,"deleted_at":null,"user_deleted":false,"edit_reason":null,"can_view_edit_history":true,"wiki":false,"can_accept_answer":false,"can_unaccept_answer":false,"accepted_answer":false}],"stream":[3657,3677]},"timeline_lookup":[[1,2898],[2,2897]],"suggested_topics":[{"id":7332,"title":"Action RPG Game with Urho3D and Entt","fancy_title":"Action RPG Game with Urho3D and Entt","slug":"action-rpg-game-with-urho3d-and-entt","posts_count":1,"reply_count":0,"highest_post_number":1,"image_url":null,"created_at":"2022-09-25T04:07:40.447Z","last_posted_at":"2022-09-25T04:07:40.526Z","bumped":true,"bumped_at":"2022-09-25T04:07:40.526Z","archetype":"regular","unseen":false,"pinned":false,"unpinned":null,"visible":true,"closed":false,"archived":false,"bookmarked":null,"liked":null,"tags_descriptions":{},"like_count":1,"views":220,"category_id":12,"featured_link":null,"has_accepted_answer":false,"posters":[{"extras":"latest single","description":"Original Poster, Most Recent Poster","user":{"id":789,"username":"codewalkerdan","name":"Codewalkerdan","avatar_template":"/user_avatar/discourse.urho3d.io/codewalkerdan/{size}/675_2.png"}}]},{"id":7108,"title":":soccer: Open Saucer","fancy_title":":soccer: Open Saucer","slug":"open-saucer","posts_count":1,"reply_count":0,"highest_post_number":1,"image_url":null,"created_at":"2021-12-22T04:04:27.024Z","last_posted_at":"2021-12-22T04:04:27.091Z","bumped":true,"bumped_at":"2021-12-22T04:04:27.091Z","archetype":"regular","unseen":false,"pinned":false,"unpinned":null,"visible":true,"closed":false,"archived":false,"bookmarked":null,"liked":null,"unicode_title":"⚽ Open Saucer","tags_descriptions":{},"like_count":1,"views":284,"category_id":12,"featured_link":null,"has_accepted_answer":false,"posters":[{"extras":"latest single","description":"Original Poster, Most Recent Poster","user":{"id":192,"username":"Modanung","name":"魔大农 𝞍𝞎𝝳 現招蜍","avatar_template":"/user_avatar/discourse.urho3d.io/modanung/{size}/3290_2.png"}}]},{"id":7114,"title":":fireworks: Multi-Mower","fancy_title":":fireworks: Multi-Mower","slug":"multi-mower","posts_count":2,"reply_count":0,"highest_post_number":2,"image_url":"https://global.discourse-cdn.com/standard17/uploads/urho3d/optimized/2X/2/21e99fb677795abba6665611690df6db44a4f724_2_1024x336.png","created_at":"2022-01-01T00:59:53.176Z","last_posted_at":"2022-01-01T10:18:14.930Z","bumped":true,"bumped_at":"2022-01-01T22:11:41.028Z","archetype":"regular","unseen":false,"pinned":false,"unpinned":null,"visible":true,"closed":false,"archived":false,"bookmarked":null,"liked":null,"unicode_title":"🎆 Multi-Mower","tags_descriptions":{},"like_count":1,"views":258,"category_id":12,"featured_link":null,"has_accepted_answer":false,"posters":[{"extras":"latest single","description":"Original Poster, Most Recent Poster","user":{"id":192,"username":"Modanung","name":"魔大农 𝞍𝞎𝝳 現招蜍","avatar_template":"/user_avatar/discourse.urho3d.io/modanung/{size}/3290_2.png"}}]},{"id":7317,"title":"New little puzzle game","fancy_title":"New little puzzle game","slug":"new-little-puzzle-game","posts_count":5,"reply_count":2,"highest_post_number":5,"image_url":null,"created_at":"2022-08-23T06:38:39.245Z","last_posted_at":"2022-09-05T19:26:29.102Z","bumped":true,"bumped_at":"2022-09-05T19:26:29.102Z","archetype":"regular","unseen":false,"pinned":false,"unpinned":null,"visible":true,"closed":false,"archived":false,"bookmarked":null,"liked":null,"tags_descriptions":{},"like_count":5,"views":232,"category_id":12,"featured_link":null,"has_accepted_answer":false,"posters":[{"extras":"latest","description":"Original Poster, Most Recent Poster","user":{"id":809,"username":"elix22","name":"","avatar_template":"/user_avatar/discourse.urho3d.io/elix22/{size}/1437_2.png"}},{"extras":null,"description":"Frequent Poster","user":{"id":484,"username":"Eugene","name":"Eugene Kozlov","avatar_template":"/user_avatar/discourse.urho3d.io/eugene/{size}/902_2.png"}}]},{"id":7357,"title":"My multi-platform game development editor","fancy_title":"My multi-platform game development editor","slug":"my-multi-platform-game-development-editor","posts_count":4,"reply_count":1,"highest_post_number":4,"image_url":null,"created_at":"2022-11-17T11:59:16.052Z","last_posted_at":"2022-11-18T02:03:35.533Z","bumped":true,"bumped_at":"2022-11-18T02:03:35.533Z","archetype":"regular","unseen":false,"pinned":false,"unpinned":null,"visible":true,"closed":false,"archived":false,"bookmarked":null,"liked":null,"tags_descriptions":{},"like_count":7,"views":140,"category_id":12,"featured_link":null,"has_accepted_answer":false,"posters":[{"extras":null,"description":"Original Poster","user":{"id":809,"username":"elix22","name":"","avatar_template":"/user_avatar/discourse.urho3d.io/elix22/{size}/1437_2.png"}},{"extras":null,"description":"Frequent Poster","user":{"id":627,"username":"George1","name":"","avatar_template":"https://avatars.discourse-cdn.com/v4/letter/g/9e8a1a/{size}.png"}},{"extras":null,"description":"Frequent Poster","user":{"id":1038,"username":"dertom","name":"Thomas Trocha","avatar_template":"/user_avatar/discourse.urho3d.io/dertom/{size}/1815_2.png"}},{"extras":"latest","description":"Most Recent Poster","user":{"id":263,"username":"1vanK","name":"","avatar_template":"/user_avatar/discourse.urho3d.io/1vank/{size}/768_2.png"}}]}],"tags_descriptions":{},"id":675,"title":"Claus of Fury","fancy_title":"Claus of Fury","posts_count":2,"created_at":"2014-12-17T11:32:30.000Z","views":402,"reply_count":0,"like_count":0,"last_posted_at":"2014-12-18T02:54:14.000Z","visible":true,"closed":false,"archived":false,"has_summary":false,"archetype":"regular","slug":"claus-of-fury","category_id":12,"word_count":50,"deleted_at":null,"user_id":140,"featured_link":null,"pinned_globally":false,"pinned_at":null,"pinned_until":null,"image_url":null,"slow_mode_seconds":0,"draft":null,"draft_key":"topic_675","draft_sequence":null,"unpinned":null,"pinned":false,"current_post_number":1,"highest_post_number":2,"deleted_by":null,"actions_summary":[{"id":4,"count":0,"hidden":false,"can_act":false},{"id":8,"count":0,"hidden":false,"can_act":false},{"id":7,"count":0,"hidden":false,"can_act":false}],"chunk_size":20,"bookmarked":false,"bookmarks":[],"topic_timer":null,"message_bus_last_id":0,"participant_count":2,"show_read_indicator":false,"thumbnails":null,"slow_mode_enabled_until":null,"tags_disable_ads":false,"details":{"can_edit":false,"notification_level":1,"participants":[{"id":48,"username":"att","name":"","avatar_template":"https://avatars.discourse-cdn.com/v4/letter/a/bcef8e/{size}.png","post_count":1,"primary_group_name":null,"flair_name":null,"flair_url":null,"flair_color":null,"flair_bg_color":null,"trust_level":2},{"id":140,"username":"practicing01","name":"","avatar_template":"https://avatars.discourse-cdn.com/v4/letter/p/b5e925/{size}.png","post_count":1,"primary_group_name":null,"flair_name":null,"flair_url":null,"flair_color":null,"flair_bg_color":null,"trust_level":1}],"created_by":{"id":140,"username":"practicing01","name":"","avatar_template":"https://avatars.discourse-cdn.com/v4/letter/p/b5e925/{size}.png"},"last_poster":{"id":48,"username":"att","name":"","avatar_template":"https://avatars.discourse-cdn.com/v4/letter/a/bcef8e/{size}.png"},"links":[{"url":"https://www.youtube.com/watch?v=N9Me64RjV-8%5B/video%5D","title":"Claus of Fury","internal":false,"attachment":false,"reflection":false,"clicks":4,"user_id":140,"domain":"www.youtube.com","root_domain":"youtube.com"},{"url":"https://play.google.com/store/apps/details?id=com.mds.cof","title":null,"internal":false,"attachment":false,"reflection":false,"clicks":2,"user_id":140,"domain":"play.google.com","root_domain":"google.com"}]}}